{
	"info": {
		"_postman_id": "a34db5fa-3c63-4d36-af8e-2d3ce38b0323",
		"name": "Taks",
		"schema": "https://schema.getpostman.com/json/collection/v2.1.0/collection.json",
		"_exporter_id": "28686115"
	},
	"item": [
		{
			"name": "data",
			"item": [
				{
					"name": "New request",
					"request": {
						"method": "POST",
						"header": [],
						"body": {
							"mode": "raw",
							"raw": "{\r\n       \r\n       \"title\": \"Configurar servidor\",\r\n       \"createdAt\": \"2024-08-25T10:00:00Z\"\r\n   }",
							"options": {
								"raw": {
									"language": "json"
								}
							}
						},
						"url": {
							"raw": "localhost:3000/api/tasks",
							"host": [
								"localhost"
							],
							"port": "3000",
							"path": [
								"api",
								"tasks"
							]
						}
					},
					"response": []
				},
				{
					"name": "New request",
					"request": {
						"method": "POST",
						"header": [],
						"body": {
							"mode": "raw",
							"raw": "{\r\n       \"title\": \"Diseñar base de datos\",\r\n       \"createdAt\": \"2024-08-26T11:00:00Z\"\r\n   }",
							"options": {
								"raw": {
									"language": "json"
								}
							}
						},
						"url": {
							"raw": "localhost:3000/api/tasks",
							"host": [
								"localhost"
							],
							"port": "3000",
							"path": [
								"api",
								"tasks"
							]
						}
					},
					"response": []
				}
			]
		},
		{
			"name": "post",
			"request": {
				"method": "POST",
				"header": [],
				"body": {
					"mode": "raw",
					"raw": "{\r\n    \"title\": \"Aprender Express\"\r\n}",
					"options": {
						"raw": {
							"language": "json"
						}
					}
				},
				"url": {
					"raw": "localhost:3000/api/tasks",
					"host": [
						"localhost"
					],
					"port": "3000",
					"path": [
						"api",
						"tasks"
					]
				}
			},
			"response": []
		},
		{
			"name": "get",
			"request": {
				"method": "GET",
				"header": [],
				"url": {
					"raw": "localhost:3000/api/tasks",
					"host": [
						"localhost"
					],
					"port": "3000",
					"path": [
						"api",
						"tasks"
					]
				}
			},
			"response": []
		},
		{
			"name": "getId",
			"request": {
				"method": "GET",
				"header": [],
				"url": {
					"raw": "localhost:3000/api/tasks/1724908082822",
					"host": [
						"localhost"
					],
					"port": "3000",
					"path": [
						"api",
						"tasks",
						"1724908082822"
					]
				}
			},
			"response": []
		},
		{
			"name": "put",
			"request": {
				"method": "PUT",
				"header": [],
				"body": {
					"mode": "raw",
					"raw": "{\r\n    \"title\": \"Aprender Express mucho\",\r\n    \"completed\": true\r\n}",
					"options": {
						"raw": {
							"language": "json"
						}
					}
				},
				"url": {
					"raw": "localhost:3000/api/tasks/1",
					"host": [
						"localhost"
					],
					"port": "3000",
					"path": [
						"api",
						"tasks",
						"1"
					]
				}
			},
			"response": []
		},
		{
			"name": "delete",
			"request": {
				"method": "DELETE",
				"header": [],
				"url": {
					"raw": "localhost:3000/api/tasks/172490809296",
					"host": [
						"localhost"
					],
					"port": "3000",
					"path": [
						"api",
						"tasks",
						"172490809296"
					]
				}
			},
			"response": []
		},
		{
			"name": "statistics",
			"request": {
				"method": "GET",
				"header": [],
				"url": {
					"raw": "localhost:3000/api/tasks/statistics",
					"host": [
						"localhost"
					],
					"port": "3000",
					"path": [
						"api",
						"tasks",
						"statistics"
					]
				}
			},
			"response": []
		}
	]
}